prmtools/__about__.py
prmtools/__init__.py
prmtools/__main__.py
prmtools/cli.py
prmtools/extraction.py
prmtools/plotting.py
prmtools/py.typed
prmtools/quality.py
prmtools/utils.py
prmtools-0.1.0.dist-info/METADATA
prmtools-0.1.0.dist-info/WHEEL
prmtools-0.1.0.dist-info/top_level.txt
prmtools-0.1.0.dist-info/RECORD
