Metadata-Version: 2.4
Name: prmtools
Version: 0.1.0
Summary: A toolkit for PRM (Parallel Reaction Monitoring) data analysis
Author: Oluwatosin Daramola
Author-email: Your Name <your.email@example.com>
Requires-Python: >=3.7
Requires-Dist: numpy
Requires-Dist: pandas
Requires-Dist: matplotlib
Requires-Dist: scipy
Requires-Dist: openpyxl
Dynamic: author
Dynamic: requires-python
